setup.py
music_vk/__init__.py
music_vk/first.py
music_vk/init.py
music_vk/menu.py
music_vk/music_play.py
music_vk/save_file.py
music_vk/scrolling.py
music_vk/scrolling1.py
music_vk/viget_download.py
music_vk.egg-info/PKG-INFO
music_vk.egg-info/SOURCES.txt
music_vk.egg-info/dependency_links.txt
music_vk.egg-info/not-zip-safe
music_vk.egg-info/requires.txt
music_vk.egg-info/top_level.txt